Metadata-Version: 2.4
Name: sym
Version: 0.3.6
Summary: Unified wrapper for symbolic manipulation libraries in Python.
Home-page: https://github.com/bjodah/sym
Author: Bjoern I. Dahlgren 
Author-email: bjodah@gmail.com
License: BSD
Classifier: Development Status :: 3 - Alpha
Classifier: License :: OSI Approved :: BSD License
Classifier: Operating System :: OS Independent
Classifier: Topic :: Scientific/Engineering
Classifier: Topic :: Scientific/Engineering :: Mathematics
License-File: LICENSE
License-File: AUTHORS
Requires-Dist: numpy
Provides-Extra: symbolic
Requires-Dist: sympy>=1.0; extra == "symbolic"
Requires-Dist: pysym; extra == "symbolic"
Requires-Dist: symcxx>=0.1.10; extra == "symbolic"
Requires-Dist: diofant; extra == "symbolic"
Provides-Extra: docs
Requires-Dist: Sphinx; extra == "docs"
Requires-Dist: sphinx_rtd_theme; extra == "docs"
Requires-Dist: numpydoc; extra == "docs"
Provides-Extra: testing
Requires-Dist: pytest; extra == "testing"
Requires-Dist: pytest-cov; extra == "testing"
Requires-Dist: pytest-flakes; extra == "testing"
Requires-Dist: pytest-pep8; extra == "testing"
Provides-Extra: all
Requires-Dist: sympy>=1.0; extra == "all"
Requires-Dist: pysym; extra == "all"
Requires-Dist: symcxx>=0.1.10; extra == "all"
Requires-Dist: diofant; extra == "all"
Requires-Dist: Sphinx; extra == "all"
Requires-Dist: sphinx_rtd_theme; extra == "all"
Requires-Dist: numpydoc; extra == "all"
Requires-Dist: pytest; extra == "all"
Requires-Dist: pytest-cov; extra == "all"
Requires-Dist: pytest-flakes; extra == "all"
Requires-Dist: pytest-pep8; extra == "all"
Dynamic: author
Dynamic: author-email
Dynamic: classifier
Dynamic: description
Dynamic: home-page
Dynamic: license
Dynamic: license-file
Dynamic: provides-extra
Dynamic: requires-dist
Dynamic: summary
